atexplain/__init__.py
atexplain/egine.py
autexplain-0.1.0.dist-info/METADATA
autexplain-0.1.0.dist-info/WHEEL
autexplain-0.1.0.dist-info/top_level.txt
autexplain-0.1.0.dist-info/RECORD
