Metadata-Version: 2.4
Name: autexplain
Version: 0.1.0
Summary: Автоматически спрашивает объяснение кода при завершении программы
Requires-Python: >=3.7
Dynamic: requires-python
Dynamic: summary
